vk/__init__.py
vk/api.py
vk/attachments.py
vk/auth.py
vk/base.py
vk/comment.py
vk/database.py
vk/error.py
vk/fetch.py
vk/friends.py
vk/groups.py
vk/messages.py
vk/photos.py
vk/polls.py
vk/users.py
vk/wall.py
py_vkontakte-5.76.0.dist-info/LICENSE
py_vkontakte-5.76.0.dist-info/METADATA
py_vkontakte-5.76.0.dist-info/WHEEL
py_vkontakte-5.76.0.dist-info/top_level.txt
py_vkontakte-5.76.0.dist-info/RECORD
