Metadata-Version: 2.1
Name: py-vkontakte
Version: 5.76.0
Summary: Python API wrapper around vk.com API
Home-page: https://github.com/sgaynetdinov/py-vkontakte
Author: Sergey Gaynetdinov
Author-email: s.gaynetdinov@gmail.com
License: MIT License
Keywords: vk.com,vk,vkontakte,vk api
Platform: UNKNOWN
Classifier: License :: OSI Approved :: MIT License
Classifier: Programming Language :: Python
Classifier: Programming Language :: Python :: 3
Classifier: Programming Language :: Python :: 3.6
Classifier: Programming Language :: Python :: 3.7
Classifier: Programming Language :: Python :: Implementation :: PyPy
Classifier: Programming Language :: Python :: Implementation :: CPython
Classifier: Topic :: Software Development :: Libraries :: Python Modules
